prosperworks
