Metadata-Version: 1.1
Name: prosperworks
Version: 0.1.4
Summary: A simple python wrapper for the ProsperWorks API
Home-page: https://github.com/tizz98/prosperworks-api
Author: Elijah Wilson
Author-email: elijah@elijahwilson.me
License: MIT
Download-URL: https://github.com/tizz98/prosperworks-api/tarball/0.1.4
Keywords: prosperworks api
Platform: UNKNOWN
Classifier: Development Status :: 4 - Beta
Classifier: Intended Audience :: Developers
Classifier: Topic :: Software Development :: Libraries
Classifier: License :: OSI Approved :: MIT License
Classifier: Programming Language :: Python :: 2
Classifier: Programming Language :: Python :: 2.6
Classifier: Programming Language :: Python :: 2.7
